LICENSE
MANIFEST.in
Makefile
README.rst
setup.py
barcode/DejaVuSansMono.ttf
barcode/__init__.py
barcode/base.py
barcode/codex.py
barcode/ean.py
barcode/errors.py
barcode/isxn.py
barcode/itf.py
barcode/pybarcode.py
barcode/upc.py
barcode/writer.py
barcode/charsets/__init__.py
barcode/charsets/code128.py
barcode/charsets/code39.py
barcode/charsets/ean.py
barcode/charsets/itf.py
docs/Makefile
docs/barcode.rst
docs/codes.rst
docs/commandline.rst
docs/conf.py
docs/index.rst
docs/license.rst
docs/make.bat
docs/images/viivakoodi.png
docs/images/viivakoodi_small.png
docs/writers/create_writer.rst
docs/writers/image.rst
docs/writers/index.rst
docs/writers/svg.rst
tiqetsbarcode.egg-info/PKG-INFO
tiqetsbarcode.egg-info/SOURCES.txt
tiqetsbarcode.egg-info/dependency_links.txt
tiqetsbarcode.egg-info/entry_points.txt
tiqetsbarcode.egg-info/top_level.txt