Metadata-Version: 1.1
Name: tiqetsbarcode
Version: 0.8.0
Summary: Create standard barcodes with Python. No external modules needed (optional PIL support included).
Home-page: https://bitbucket.org/tiqets/barcode
Author: Thorsten Weimann, Alexander Shorin
Author-email: developer@tiqets.com
License: MIT
Platform: UNKNOWN
Classifier: Development Status :: 4 - Beta
Classifier: Environment :: Console
Classifier: Intended Audience :: Developers
Classifier: License :: OSI Approved :: MIT License
Classifier: Operating System :: OS Independent
Classifier: Programming Language :: Python
Classifier: Programming Language :: Python :: 2
Classifier: Programming Language :: Python :: 2.6
Classifier: Programming Language :: Python :: 2.7
Classifier: Programming Language :: Python :: 3
Classifier: Programming Language :: Python :: 3.3
Classifier: Programming Language :: Python :: 3.4
Classifier: Topic :: Software Development :: Libraries :: Python Modules
Classifier: Topic :: Multimedia :: Graphics
